i2c_slave.v


module i2c_slave(
	inout sda,
	inout scl
	);
	
	localparam ADDRESS = 7'b0101010;
	
	localparam READ_ADDR = 0;
	localparam SEND_ACK = 1;
	localparam READ_DATA = 2;
	localparam WRITE_DATA = 3;
	localparam SEND_ACK2 = 4;
	
	reg [7:0] addr;
	reg [7:0] counter;
	reg [7:0] state = 0;
	reg [7:0] data_in = 0;
	reg [7:0] data_out = 8'b11001100;
	reg sda_out = 0;
	reg sda_in = 0;
	reg start = 0;
	reg write_enable = 0;
	
	assign sda = (write_enable == 1) ? sda_out : 'bz;
	
	always @(negedge sda) begin
		if ((start == 0) && (scl == 1)) begin
			start <= 1;	
			counter <= 7;
		end
	end
	
	always @(posedge sda) begin
		if ((start == 1) && (scl == 1)) begin
			state <= READ_ADDR;
			start <= 0;
			write_enable <= 0;
		end
	end
	
	always @(posedge scl) begin
		if (start == 1) begin
			case(state)
				READ_ADDR: begin
					addr[counter] <= sda;
					if(counter == 0) state <= SEND_ACK;
					else counter <= counter - 1;					
				end
				
				SEND_ACK: begin
					if(addr[7:1] == ADDRESS) begin
						counter <= 7;
						if(addr[0] == 0) begin 
							state <= READ_DATA;
						end
						else state <= WRITE_DATA;
					end else begin	
						state <= READ_ADDR;
						start <= 0;
						write_enable <= 0;
					end
				end
				
				READ_DATA: begin
					data_in[counter] <= sda;
					if(counter == 0) begin
						state <= SEND_ACK2;
					end else counter <= counter - 1;
				end
				
				SEND_ACK2: begin
					state <= READ_ADDR;					
				end
				
				WRITE_DATA: begin
					if(counter == 0) state <= READ_ADDR;
					else counter <= counter - 1;		
				end
				
			endcase
		end
	end
	
	always @(negedge scl) begin
		case(state)
			
			READ_ADDR: begin
				write_enable <= 0;			
			end
			
			SEND_ACK: begin
				sda_out <= 0;
				write_enable <= 1;	
			end
			
			READ_DATA: begin
				write_enable <= 0;
			end
			
			WRITE_DATA: begin
				sda_out <= data_out[counter];
				write_enable <= 1;
			end
			
			SEND_ACK2: begin
				sda_out <= 0;
				write_enable <= 1;
			end
		endcase
	end
endmodule

i2c_master.v
`timescale 1ns / 1ps





module i2c_master(
	input wire clk,
	input wire rst,
	input wire [6:0] addr,
	input wire [7:0] data_in,
	input wire enable,
	input wire rw,

	output reg [7:0] data_out,
	output wire ready,

	inout i2c_sda,
	inout wire i2c_scl
	);

	localparam IDLE = 0;
	localparam START = 1;
	localparam ADDRESS = 2;
	localparam READ_ACK = 3;
	localparam WRITE_DATA = 4;
	localparam WRITE_ACK = 5;
	localparam READ_DATA = 6;
	localparam READ_ACK2 = 7;
	localparam STOP = 8;
	
	localparam DIVIDE_BY = 4;

	reg [7:0] state;
	reg [7:0] saved_addr;
	reg [7:0] saved_data;
	reg [7:0] counter;
	reg [7:0] counter2 = 0;
	reg write_enable;
	reg sda_out;
	reg i2c_scl_enable = 0;
	reg i2c_clk = 1;

	assign ready = ((rst == 0) && (state == IDLE)) ? 1 : 0;
	assign i2c_scl = (i2c_scl_enable == 0 ) ? 1 : i2c_clk;
	assign i2c_sda = (write_enable == 1) ? sda_out : 'bz;
	
	always @(posedge clk) begin
		if (counter2 == (DIVIDE_BY/2) - 1) begin
			i2c_clk <= ~i2c_clk;
			counter2 <= 0;
		end
		else counter2 <= counter2 + 1;
	end 
	
	always @(negedge i2c_clk, posedge rst) begin
		if(rst == 1) begin
			i2c_scl_enable <= 0;
		end else begin
			if ((state == IDLE) || (state == START) || (state == STOP)) begin
				i2c_scl_enable <= 0;
			end else begin
				i2c_scl_enable <= 1;
			end
		end
	
	end


	always @(posedge i2c_clk, posedge rst) begin
		if(rst == 1) begin
			state <= IDLE;
		end		
		else begin
			case(state)
			
				IDLE: begin
					if (enable) begin
						state <= START;
						saved_addr <= {addr, rw};
						saved_data <= data_in;
					end
					else state <= IDLE;
				end

				START: begin
					counter <= 7;
					state <= ADDRESS;
				end

				ADDRESS: begin
					if (counter == 0) begin 
						state <= READ_ACK;
					end else counter <= counter - 1;
				end

				READ_ACK: begin
					if (i2c_sda == 0) begin
						counter <= 7;
						if(saved_addr[0] == 0) state <= WRITE_DATA;
						else state <= READ_DATA;
					end else state <= STOP;
				end

				WRITE_DATA: begin
					if(counter == 0) begin
						state <= READ_ACK2;
					end else counter <= counter - 1;
				end
				
				READ_ACK2: begin
					if ((i2c_sda == 0) && (enable == 1)) state <= IDLE;
					else state <= STOP;
				end

				READ_DATA: begin
					data_out[counter] <= i2c_sda;
					if (counter == 0) state <= WRITE_ACK;
					else counter <= counter - 1;
				end
				
				WRITE_ACK: begin
					state <= STOP;
				end

				STOP: begin
					state <= IDLE;
				end
			endcase
		end
	end
	
	always @(negedge i2c_clk, posedge rst) begin
		if(rst == 1) begin
			write_enable <= 1;
			sda_out <= 1;
		end else begin
			case(state)
				
				START: begin
					write_enable <= 1;
					sda_out <= 0;
				end
				
				ADDRESS: begin
					sda_out <= saved_addr[counter];
				end
				
				READ_ACK: begin
					write_enable <= 0;
				end
				
				WRITE_DATA: begin 
					write_enable <= 1;
					sda_out <= saved_data[counter];
				end
				
				WRITE_ACK: begin
					write_enable <= 1;
					sda_out <= 0;
				end
				
				READ_DATA: begin
					write_enable <= 0;				
				end
				
				STOP: begin
					write_enable <= 1;
					sda_out <= 1;
				end
			endcase
		end
	end

endmodule

i2c_master_tb.v
`timescale 1ns / 1ps

module i2c_master_tb;

	// Inputs
	reg clk;
	reg rst;
	reg [6:0] addr;
	reg [7:0] data_in;
	reg enable;
	reg rw;

	// Outputs
	wire [7:0] data_out;
	wire ready; 

	// Bidirs
	wire i2c_sda;
	wire i2c_scl;

	// Instantiate the Unit Under Test (UUT)
	i2c_master master (
		.clk(clk), 
		.rst(rst), 
		.addr(addr), 
		.data_in(data_in), 
		.enable(enable), 
		.rw(rw), 
		.data_out(data_out), 
		.ready(ready), 
		.i2c_sda(i2c_sda), 
		.i2c_scl(i2c_scl)
	);
	
		
	i2c_slave slave (
    .sda(i2c_sda), 
    .scl(i2c_scl)
    );
	
	initial begin
		clk = 0;
		forever begin
			clk = #1 ~clk;
		end		
	end

	initial begin

        $dumpfile("dump.vcd");
        $dumpvars(0, i2c_master_tb);
		// Initialize Inputs
		clk = 0;
		rst = 1;

		// Wait 100 ns for global reset to finish
		#100;
        
		// Add stimulus here
		rst = 0;		

		addr = 7'b0101010;
		data_in = 8'b10101010;
		rw = 1;	
		enable = 1;
		#10;
		enable = 0;
				
		#500
		$finish;
		
	end      
endmodule

dump2.vcd
$date
	Tue Jun 03 16:50:00 2025
$end
$version
	Icarus Verilog
$end
$timescale
	1ps
$end
$scope module i2c_master_tb $end
$var wire 1 ! i2c_sda $end
$var wire 1 " ready $end
$var wire 1 # i2c_scl $end
$var wire 8 $ data_out [7:0] $end
$var reg 7 % addr [6:0] $end
$var reg 1 & clk $end
$var reg 8 ' data_in [7:0] $end
$var reg 1 ( enable $end
$var reg 1 ) rst $end
$var reg 1 * rw $end
$scope module master $end
$var wire 7 + addr [6:0] $end
$var wire 1 & clk $end
$var wire 8 , data_in [7:0] $end
$var wire 1 ( enable $end
$var wire 1 ! i2c_sda $end
$var wire 1 ) rst $end
$var wire 1 * rw $end
$var wire 1 " ready $end
$var wire 1 # i2c_scl $end
$var parameter 32 - ADDRESS $end
$var parameter 32 . DIVIDE_BY $end
$var parameter 32 / IDLE $end
$var parameter 32 0 READ_ACK $end
$var parameter 32 1 READ_ACK2 $end
$var parameter 32 2 READ_DATA $end
$var parameter 32 3 START $end
$var parameter 32 4 STOP $end
$var parameter 32 5 WRITE_ACK $end
$var parameter 32 6 WRITE_DATA $end
$var reg 8 7 counter [7:0] $end
$var reg 8 8 counter2 [7:0] $end
$var reg 8 9 data_out [7:0] $end
$var reg 1 : i2c_clk $end
$var reg 1 ; i2c_scl_enable $end
$var reg 8 < saved_addr [7:0] $end
$var reg 8 = saved_data [7:0] $end
$var reg 1 > sda_out $end
$var reg 8 ? state [7:0] $end
$var reg 1 @ write_enable $end
$upscope $end
$scope module slave $end
$var wire 1 # scl $end
$var wire 1 ! sda $end
$var parameter 7 A ADDRESS $end
$var parameter 32 B READ_ADDR $end
$var parameter 32 C READ_DATA $end
$var parameter 32 D SEND_ACK $end
$var parameter 32 E SEND_ACK2 $end
$var parameter 32 F WRITE_DATA $end
$var reg 8 G addr [7:0] $end
$var reg 8 H counter [7:0] $end
$var reg 8 I data_in [7:0] $end
$var reg 8 J data_out [7:0] $end
$var reg 1 K sda_in $end
$var reg 1 L sda_out $end
$var reg 1 M start $end
$var reg 8 N state [7:0] $end
$var reg 1 O write_enable $end
$upscope $end
$upscope $end
$enddefinitions $end
$comment Show the parameter values. $end
$dumpall
b11 F
b100 E
b1 D
b10 C
b0 B
b101010 A
b100 6
b101 5
b1000 4
b1 3
b110 2
b111 1
b11 0
b0 /
b100 .
b10 -
$end
#0
$dumpvars
0O
b0 N
0M
0L
0K
b11001100 J
b0 I
bx H
bx G
1@
b0 ?
1>
bx =
bx <
0;
1:
bx 9
b0 8
bx 7
bx ,
bx +
x*
1)
x(
bx '
0&
bx %
bx $
1#
0"
1!
$end
#1000
b1 8
1&
#2000
0&
#3000
b0 8
0:
1&
#4000
0&
#5000
b1 8
1&
#6000
0&
#7000
b0 8
1:
1&
#8000
0&
#9000
b1 8
1&
#10000
0&
#11000
b0 8
0:
1&
#12000
0&
#13000
b1 8
1&
#14000
0&
#15000
b0 8
1:
1&
#16000
0&
#17000
b1 8
1&
#18000
0&
#19000
b0 8
0:
1&
#20000
0&
#21000
b1 8
1&
#22000
0&
#23000
b0 8
1:
1&
#24000
0&
#25000
b1 8
1&
#26000
0&
#27000
b0 8
0:
1&
#28000
0&
#29000
b1 8
1&
#30000
0&
#31000
b0 8
1:
1&
#32000
0&
#33000
b1 8
1&
#34000
0&
#35000
b0 8
0:
1&
#36000
0&
#37000
b1 8
1&
#38000
0&
#39000
b0 8
1:
1&
#40000
0&
#41000
b1 8
1&
#42000
0&
#43000
b0 8
0:
1&
#44000
0&
#45000
b1 8
1&
#46000
0&
#47000
b0 8
1:
1&
#48000
0&
#49000
b1 8
1&
#50000
0&
#51000
b0 8
0:
1&
#52000
0&
#53000
b1 8
1&
#54000
0&
#55000
b0 8
1:
1&
#56000
0&
#57000
b1 8
1&
#58000
0&
#59000
b0 8
0:
1&
#60000
0&
#61000
b1 8
1&
#62000
0&
#63000
b0 8
1:
1&
#64000
0&
#65000
b1 8
1&
#66000
0&
#67000
b0 8
0:
1&
#68000
0&
#69000
b1 8
1&
#70000
0&
#71000
b0 8
1:
1&
#72000
0&
#73000
b1 8
1&
#74000
0&
#75000
b0 8
0:
1&
#76000
0&
#77000
b1 8
1&
#78000
0&
#79000
b0 8
1:
1&
#80000
0&
#81000
b1 8
1&
#82000
0&
#83000
b0 8
0:
1&
#84000
0&
#85000
b1 8
1&
#86000
0&
#87000
b0 8
1:
1&
#88000
0&
#89000
b1 8
1&
#90000
0&
#91000
b0 8
0:
1&
#92000
0&
#93000
b1 8
1&
#94000
0&
#95000
b0 8
1:
1&
#96000
0&
#97000
b1 8
1&
#98000
0&
#99000
b0 8
0:
1&
#100000
1"
0&
1(
1*
b10101010 '
b10101010 ,
b101010 %
b101010 +
0)
#101000
b1 8
1&
#102000
0&
#103000
0"
b10101010 =
b1010101 <
b1 ?
b0 8
1:
1&
#104000
0&
#105000
b1 8
1&
#106000
0&
#107000
b111 H
1M
0!
0>
b0 8
0:
1&
#108000
0&
#109000
b1 8
1&
#110000
0&
0(
#111000
b10 ?
b111 7
b0 8
1:
1&
#112000
0&
#113000
b1 8
1&
#114000
0&
#115000
0#
1;
b0 8
0:
1&
#116000
0&
#117000
b1 8
1&
#118000
0&
#119000
b110 H
b0xxxxxxx G
b110 7
1#
b0 8
1:
1&
#120000
0&
#121000
b1 8
1&
#122000
0&
#123000
1!
1>
0#
b0 8
0:
1&
#124000
0&
#125000
b1 8
1&
#126000
0&
#127000
b101 H
b1xxxxxx G
b101 7
1#
b0 8
1:
1&
#128000
0&
#129000
b1 8
1&
#130000
0&
#131000
0!
0>
0#
b0 8
0:
1&
#132000
0&
#133000
b1 8
1&
#134000
0&
#135000
b100 H
b10xxxxx G
b100 7
1#
b0 8
1:
1&
#136000
0&
#137000
b1 8
1&
#138000
0&
#139000
1!
1>
0#
b0 8
0:
1&
#140000
0&
#141000
b1 8
1&
#142000
0&
#143000
b11 H
b101xxxx G
b11 7
1#
b0 8
1:
1&
#144000
0&
#145000
b1 8
1&
#146000
0&
#147000
0!
0>
0#
b0 8
0:
1&
#148000
0&
#149000
b1 8
1&
#150000
0&
#151000
b10 H
b1010xxx G
b10 7
1#
b0 8
1:
1&
#152000
0&
#153000
b1 8
1&
#154000
0&
#155000
1!
1>
0#
b0 8
0:
1&
#156000
0&
#157000
b1 8
1&
#158000
0&
#159000
b1 H
b10101xx G
b1 7
1#
b0 8
1:
1&
#160000
0&
#161000
b1 8
1&
#162000
0&
#163000
0!
0>
0#
b0 8
0:
1&
#164000
0&
#165000
b1 8
1&
#166000
0&
#167000
b0 H
b101010x G
b0 7
1#
b0 8
1:
1&
#168000
0&
#169000
b1 8
1&
#170000
0&
#171000
1!
1>
0#
b0 8
0:
1&
#172000
0&
#173000
b1 8
1&
#174000
0&
#175000
b1 N
b1010101 G
b11 ?
1#
b0 8
1:
1&
#176000
0&
#177000
b1 8
1&
#178000
0&
#179000
0!
1O
0@
0#
b0 8
0:
1&
#180000
0&
#181000
b1 8
1&
#182000
0&
#183000
b11 N
b111 H
b110 ?
b111 7
1#
b0 8
1:
1&
#184000
0&
#185000
b1 8
1&
#186000
0&
#187000
1!
1L
0#
b0 8
0:
1&
#188000
0&
#189000
b1 8
1&
#190000
0&
#191000
b110 H
b110 7
b1xxxxxxx $
b1xxxxxxx 9
1#
b0 8
1:
1&
#192000
0&
#193000
b1 8
1&
#194000
0&
#195000
0#
b0 8
0:
1&
#196000
0&
#197000
b1 8
1&
#198000
0&
#199000
b101 H
b101 7
b11xxxxxx $
b11xxxxxx 9
1#
b0 8
1:
1&
#200000
0&
#201000
b1 8
1&
#202000
0&
#203000
0!
0L
0#
b0 8
0:
1&
#204000
0&
#205000
b1 8
1&
#206000
0&
#207000
b100 H
b100 7
b110xxxxx $
b110xxxxx 9
1#
b0 8
1:
1&
#208000
0&
#209000
b1 8
1&
#210000
0&
#211000
0#
b0 8
0:
1&
#212000
0&
#213000
b1 8
1&
#214000
0&
#215000
b11 H
b11 7
b1100xxxx $
b1100xxxx 9
1#
b0 8
1:
1&
#216000
0&
#217000
b1 8
1&
#218000
0&
#219000
1!
1L
0#
b0 8
0:
1&
#220000
0&
#221000
b1 8
1&
#222000
0&
#223000
b10 H
b10 7
b11001xxx $
b11001xxx 9
1#
b0 8
1:
1&
#224000
0&
#225000
b1 8
1&
#226000
0&
#227000
0#
b0 8
0:
1&
#228000
0&
#229000
b1 8
1&
#230000
0&
#231000
b1 H
b1 7
b110011xx $
b110011xx 9
1#
b0 8
1:
1&
#232000
0&
#233000
b1 8
1&
#234000
0&
#235000
0!
0L
0#
b0 8
0:
1&
#236000
0&
#237000
b1 8
1&
#238000
0&
#239000
b0 H
b0 7
b1100110x $
b1100110x 9
1#
b0 8
1:
1&
#240000
0&
#241000
b1 8
1&
#242000
0&
#243000
0#
b0 8
0:
1&
#244000
0&
#245000
b1 8
1&
#246000
0&
#247000
b0 N
b101 ?
b11001100 $
b11001100 9
1#
b0 8
1:
1&
#248000
0&
#249000
b1 8
1&
#250000
0&
#251000
0O
0>
1@
0#
b0 8
0:
1&
#252000
0&
#253000
b1 8
1&
#254000
0&
#255000
b1 N
b1010100 G
b1000 ?
1#
b0 8
1:
1&
#256000
0&
#257000
b1 8
1&
#258000
0&
#259000
b111 H
0M
b10 N
1!
0O
1>
0;
1#
b0 8
0:
1&
#260000
0&
#261000
b1 8
1&
#262000
0&
#263000
1"
b0 ?
b0 8
1:
1&
#264000
0&
#265000
b1 8
1&
#266000
0&
#267000
b0 8
0:
1&
#268000
0&
#269000
b1 8
1&
#270000
0&
#271000
b0 8
1:
1&
#272000
0&
#273000
b1 8
1&
#274000
0&
#275000
b0 8
0:
1&
#276000
0&
#277000
b1 8
1&
#278000
0&
#279000
b0 8
1:
1&
#280000
0&
#281000
b1 8
1&
#282000
0&
#283000
b0 8
0:
1&
#284000
0&
#285000
b1 8
1&
#286000
0&
#287000
b0 8
1:
1&
#288000
0&
#289000
b1 8
1&
#290000
0&
#291000
b0 8
0:
1&
#292000
0&
#293000
b1 8
1&
#294000
0&
#295000
b0 8
1:
1&
#296000
0&
#297000
b1 8
1&
#298000
0&
#299000
b0 8
0:
1&
#300000
0&
#301000
b1 8
1&
#302000
0&
#303000
b0 8
1:
1&
#304000
0&
#305000
b1 8
1&
#306000
0&
#307000
b0 8
0:
1&
#308000
0&
#309000
b1 8
1&
#310000
0&
#311000
b0 8
1:
1&
#312000
0&
#313000
b1 8
1&
#314000
0&
#315000
b0 8
0:
1&
#316000
0&
#317000
b1 8
1&
#318000
0&
#319000
b0 8
1:
1&
#320000
0&
#321000
b1 8
1&
#322000
0&
#323000
b0 8
0:
1&
#324000
0&
#325000
b1 8
1&
#326000
0&
#327000
b0 8
1:
1&
#328000
0&
#329000
b1 8
1&
#330000
0&
#331000
b0 8
0:
1&
#332000
0&
#333000
b1 8
1&
#334000
0&
#335000
b0 8
1:
1&
#336000
0&
#337000
b1 8
1&
#338000
0&
#339000
b0 8
0:
1&
#340000
0&
#341000
b1 8
1&
#342000
0&
#343000
b0 8
1:
1&
#344000
0&
#345000
b1 8
1&
#346000
0&
#347000
b0 8
0:
1&
#348000
0&
#349000
b1 8
1&
#350000
0&
#351000
b0 8
1:
1&
#352000
0&
#353000
b1 8
1&
#354000
0&
#355000
b0 8
0:
1&
#356000
0&
#357000
b1 8
1&
#358000
0&
#359000
b0 8
1:
1&
#360000
0&
#361000
b1 8
1&
#362000
0&
#363000
b0 8
0:
1&
#364000
0&
#365000
b1 8
1&
#366000
0&
#367000
b0 8
1:
1&
#368000
0&
#369000
b1 8
1&
#370000
0&
#371000
b0 8
0:
1&
#372000
0&
#373000
b1 8
1&
#374000
0&
#375000
b0 8
1:
1&
#376000
0&
#377000
b1 8
1&
#378000
0&
#379000
b0 8
0:
1&
#380000
0&
#381000
b1 8
1&
#382000
0&
#383000
b0 8
1:
1&
#384000
0&
#385000
b1 8
1&
#386000
0&
#387000
b0 8
0:
1&
#388000
0&
#389000
b1 8
1&
#390000
0&
#391000
b0 8
1:
1&
#392000
0&
#393000
b1 8
1&
#394000
0&
#395000
b0 8
0:
1&
#396000
0&
#397000
b1 8
1&
#398000
0&
#399000
b0 8
1:
1&
#400000
0&
#401000
b1 8
1&
#402000
0&
#403000
b0 8
0:
1&
#404000
0&
#405000
b1 8
1&
#406000
0&
#407000
b0 8
1:
1&
#408000
0&
#409000
b1 8
1&
#410000
0&
#411000
b0 8
0:
1&
#412000
0&
#413000
b1 8
1&
#414000
0&
#415000
b0 8
1:
1&
#416000
0&
#417000
b1 8
1&
#418000
0&
#419000
b0 8
0:
1&
#420000
0&
#421000
b1 8
1&
#422000
0&
#423000
b0 8
1:
1&
#424000
0&
#425000
b1 8
1&
#426000
0&
#427000
b0 8
0:
1&
#428000
0&
#429000
b1 8
1&
#430000
0&
#431000
b0 8
1:
1&
#432000
0&
#433000
b1 8
1&
#434000
0&
#435000
b0 8
0:
1&
#436000
0&
#437000
b1 8
1&
#438000
0&
#439000
b0 8
1:
1&
#440000
0&
#441000
b1 8
1&
#442000
0&
#443000
b0 8
0:
1&
#444000
0&
#445000
b1 8
1&
#446000
0&
#447000
b0 8
1:
1&
#448000
0&
#449000
b1 8
1&
#450000
0&
#451000
b0 8
0:
1&
#452000
0&
#453000
b1 8
1&
#454000
0&
#455000
b0 8
1:
1&
#456000
0&
#457000
b1 8
1&
#458000
0&
#459000
b0 8
0:
1&
#460000
0&
#461000
b1 8
1&
#462000
0&
#463000
b0 8
1:
1&
#464000
0&
#465000
b1 8
1&
#466000
0&
#467000
b0 8
0:
1&
#468000
0&
#469000
b1 8
1&
#470000
0&
#471000
b0 8
1:
1&
#472000
0&
#473000
b1 8
1&
#474000
0&
#475000
b0 8
0:
1&
#476000
0&
#477000
b1 8
1&
#478000
0&
#479000
b0 8
1:
1&
#480000
0&
#481000
b1 8
1&
#482000
0&
#483000
b0 8
0:
1&
#484000
0&
#485000
b1 8
1&
#486000
0&
#487000
b0 8
1:
1&
#488000
0&
#489000
b1 8
1&
#490000
0&
#491000
b0 8
0:
1&
#492000
0&
#493000
b1 8
1&
#494000
0&
#495000
b0 8
1:
1&
#496000
0&
#497000
b1 8
1&
#498000
0&
#499000
b0 8
0:
1&
#500000
0&
#501000
b1 8
1&
#502000
0&
#503000
b0 8
1:
1&
#504000
0&
#505000
b1 8
1&
#506000
0&
#507000
b0 8
0:
1&
#508000
0&
#509000
b1 8
1&
#510000
0&
#511000
b0 8
1:
1&
#512000
0&
#513000
b1 8
1&
#514000
0&
#515000
b0 8
0:
1&
#516000
0&
#517000
b1 8
1&
#518000
0&
#519000
b0 8
1:
1&
#520000
0&
#521000
b1 8
1&
#522000
0&
#523000
b0 8
0:
1&
#524000
0&
#525000
b1 8
1&
#526000
0&
#527000
b0 8
1:
1&
#528000
0&
#529000
b1 8
1&
#530000
0&
#531000
b0 8
0:
1&
#532000
0&
#533000
b1 8
1&
#534000
0&
#535000
b0 8
1:
1&
#536000
0&
#537000
b1 8
1&
#538000
0&
#539000
b0 8
0:
1&
#540000
0&
#541000
b1 8
1&
#542000
0&
#543000
b0 8
1:
1&
#544000
0&
#545000
b1 8
1&
#546000
0&
#547000
b0 8
0:
1&
#548000
0&
#549000
b1 8
1&
#550000
0&
#551000
b0 8
1:
1&
#552000
0&
#553000
b1 8
1&
#554000
0&
#555000
b0 8
0:
1&
#556000
0&
#557000
b1 8
1&
#558000
0&
#559000
b0 8
1:
1&
#560000
0&
#561000
b1 8
1&
#562000
0&
#563000
b0 8
0:
1&
#564000
0&
#565000
b1 8
1&
#566000
0&
#567000
b0 8
1:
1&
#568000
0&
#569000
b1 8
1&
#570000
0&
#571000
b0 8
0:
1&
#572000
0&
#573000
b1 8
1&
#574000
0&
#575000
b0 8
1:
1&
#576000
0&
#577000
b1 8
1&
#578000
0&
#579000
b0 8
0:
1&
#580000
0&
#581000
b1 8
1&
#582000
0&
#583000
b0 8
1:
1&
#584000
0&
#585000
b1 8
1&
#586000
0&
#587000
b0 8
0:
1&
#588000
0&
#589000
b1 8
1&
#590000
0&
#591000
b0 8
1:
1&
#592000
0&
#593000
b1 8
1&
#594000
0&
#595000
b0 8
0:
1&
#596000
0&
#597000
b1 8
1&
#598000
0&
#599000
b0 8
1:
1&
#600000
0&
#601000
b1 8
1&
#602000
0&
#603000
b0 8
0:
1&
#604000
0&
#605000
b1 8
1&
#606000
0&
#607000
b0 8
1:
1&
#608000
0&
#609000
b1 8
1&
